eveio/__init__.py
eveio-0.1.0.dist-info/WHEEL
eveio-0.1.0.dist-info/METADATA
eveio-0.1.0.dist-info/RECORD
