Metadata-Version: 1.2
Name: eveio
Version: 0.1.0
Summary: Work in progress eve online api wrapper
Home-page: http://github.com/simonwoodburyforget/eveio
License: UNKNOWN
Author: Simon Woodbury-Forget
Author-email: simonwoodburyforget@gmail.com
